ovos_intent_plugin_adapt/__init__.py
ovos_intent_plugin_adapt/version.py
ovos_intent_plugin_adapt-0.0.0a12.dist-info/LICENSE
ovos_intent_plugin_adapt-0.0.0a12.dist-info/METADATA
ovos_intent_plugin_adapt-0.0.0a12.dist-info/WHEEL
ovos_intent_plugin_adapt-0.0.0a12.dist-info/entry_points.txt
ovos_intent_plugin_adapt-0.0.0a12.dist-info/top_level.txt
ovos_intent_plugin_adapt-0.0.0a12.dist-info/zip-safe
ovos_intent_plugin_adapt-0.0.0a12.dist-info/RECORD
